jget/__init__.py
jget/jget.py
jget-0.1.0.dist-info/METADATA
jget-0.1.0.dist-info/RECORD
jget-0.1.0.dist-info/WHEEL
jget-0.1.0.dist-info/entry_points.txt
jget-0.1.0.dist-info/top_level.txt
