Metadata-Version: 2.1
Name: jget
Version: 0.1.0
Summary: File downloader
Home-page: https://github.com/thisisjustinm/
Author: Justin M.
Author-email: thisisjustinm@outlook.com
License: MIT
Platform: UNKNOWN
Requires-Dist: requests
Requires-Dist: argparse
Requires-Dist: validators
Requires-Dist: tqdm
